llama_parser/__init__.py
llama_parser/base.py
llama_parser-0.1.2.dist-info/LICENSE
llama_parser-0.1.2.dist-info/METADATA
llama_parser-0.1.2.dist-info/WHEEL
llama_parser-0.1.2.dist-info/RECORD
