Metadata-Version: 2.1
Name: llama-parser
Version: 0.1.2
Summary: Parse files into RAG-Optimized formats.
License: MIT
Author: Logan Markewich
Author-email: logan@llamaindex.ai
Requires-Python: >=3.8.1,<4.0
Classifier: License :: OSI Approved :: MIT License
Classifier: Programming Language :: Python :: 3
Classifier: Programming Language :: Python :: 3.9
Classifier: Programming Language :: Python :: 3.10
Classifier: Programming Language :: Python :: 3.11
Requires-Dist: llama-index (>=0.9.40,<0.10.0)
